{
  "name": "Noemi Dark",
  "dark": true,
  "author": "Stanley Gomes",
  "editorScheme": "/themes/noemi_dark.xml",
  "ui": {
    "*": {
      "background": "#1e1e2e",
      "foreground": "#cdd6f4",
      "selectionBackground": "#45475a",
      "selectionForeground": "#cdd6f4",
      "selectionInactiveBackground": "#313244",
      "borderColor": "#45475a",
      "separatorColor": "#45475a",
      "disabledBackground": "#181825",
      "disabledForeground": "#6c7086"
    },
    "ActionButton": {
      "hoverBackground": "#313244",
      "hoverBorderColor": "#45475a",
      "pressedBackground": "#45475a",
      "pressedBorderColor": "#585b70"
    },
    "Button": {
      "startBackground": "#89b4fa",
      "endBackground": "#74c7ec",
      "startBorderColor": "#89b4fa",
      "endBorderColor": "#74c7ec",
      "foreground": "#11111b",
      "default": {
        "startBackground": "#a6e3a1",
        "endBackground": "#94e2d5",
        "startBorderColor": "#a6e3a1",
        "endBorderColor": "#94e2d5",
        "foreground": "#11111b"
      }
    },
    "ComboBox": {
      "background": "#181825",
      "selectionBackground": "#313244",
      "ArrowButton": {
        "background": "#181825",
        "nonEditableBackground": "#181825"
      }
    },
    "CompletionPopup": {
      "background": "#181825",
      "selectionBackground": "#313244"
    },
    "Component": {
      "borderColor": "#45475a",
      "focusedBorderColor": "#89b4fa",
      "focusColor": "#89b4fa",
      "errorFocusColor": "#f38ba8",
      "infoForeground": "#cdd6f4",
      "warningFocusColor": "#f9e2af"
    },
    "Editor": {
      "background": "#1e1e2e",
      "shortcutForeground": "#89dceb"
    },
    "EditorTabs": {
      "background": "#181825",
      "underlineColor": "#89b4fa",
      "inactiveUnderlineColor": "#45475a"
    },
    "Link": {
      "activeForeground": "#74c7ec",
      "hoverForeground": "#89b4fa",
      "pressedForeground": "#89dceb",
      "visitedForeground": "#b4befe"
    },
    "Panel": {
      "background": "#181825"
    },
    "Popup": {
      "background": "#181825",
      "borderColor": "#45475a"
    },
    "ProgressBar": {
      "progressColor": "#89b4fa",
      "indeterminateStartColor": "#89b4fa",
      "indeterminateEndColor": "#74c7ec"
    },
    "ScrollBar": {
      "Transparent": {
        "thumbColor": "#45475a",
        "thumbBorderColor": "#45475a",
        "hoverThumbColor": "#585b70",
        "hoverThumbBorderColor": "#585b70"
      },
      "thumbColor": "#45475a",
      "thumbBorderColor": "#45475a",
      "hoverThumbColor": "#585b70",
      "hoverThumbBorderColor": "#585b70"
    },
    "SearchEverywhere": {
      "Tab": {
        "selectedBackground": "#313244",
        "selectedForeground": "#cdd6f4"
      }
    },
    "TabbedPane": {
      "underlineColor": "#89b4fa",
      "hoverColor": "#313244",
      "contentAreaColor": "#45475a"
    },
    "Table": {
      "background": "#1e1e2e",
      "selectionBackground": "#313244",
      "selectionForeground": "#cdd6f4",
      "lightSelectionBackground": "#45475a",
      "stripeColor": "#181825"
    },
    "TextField": {
      "background": "#181825",
      "selectionBackground": "#313244"
    },
    "ToolWindow": {
      "Header": {
        "background": "#181825",
        "inactiveBackground": "#11111b"
      },
      "HeaderTab": {
        "selectedBackground": "#313244",
        "selectedInactiveBackground": "#181825",
        "hoverBackground": "#313244"
      }
    },
    "Tree": {
      "background": "#1e1e2e",
      "selectionBackground": "#313244",
      "selectionForeground": "#cdd6f4",
      "rowHeight": 24
    },
    "WelcomeScreen": {
      "background": "#1e1e2e",
      "separatorColor": "#45475a"
    }
  },
  "icons": {
    "ColorPalette": {
      "Actions.Blue": "#89b4fa",
      "Actions.Green": "#a6e3a1",
      "Actions.Red": "#f38ba8",
      "Actions.Yellow": "#f9e2af",
      "Actions.Grey": "#6c7086",
      "Objects.Blue": "#89b4fa",
      "Objects.Green": "#a6e3a1",
      "Objects.Red": "#f38ba8",
      "Objects.Yellow": "#f9e2af",
      "Objects.Purple": "#cba6f7",
      "Objects.Pink": "#f5c2e7"
    }
  }
}
